aliyunsdkimageprocess/__init__.py
aliyunsdkimageprocess/endpoint.py
aliyunsdkimageprocess/request/__init__.py
aliyunsdkimageprocess/request/v20200320/AnalyzeChestVesselRequest.py
aliyunsdkimageprocess/request/v20200320/CalcBMDRequest.py
aliyunsdkimageprocess/request/v20200320/CalcCACSRequest.py
aliyunsdkimageprocess/request/v20200320/ClassifyFNFRequest.py
aliyunsdkimageprocess/request/v20200320/DetectCovid19CadRequest.py
aliyunsdkimageprocess/request/v20200320/DetectHipKeypointXRayRequest.py
aliyunsdkimageprocess/request/v20200320/DetectKneeKeypointXRayRequest.py
aliyunsdkimageprocess/request/v20200320/DetectKneeXRayRequest.py
aliyunsdkimageprocess/request/v20200320/DetectLiverSteatosisRequest.py
aliyunsdkimageprocess/request/v20200320/DetectLungNoduleRequest.py
aliyunsdkimageprocess/request/v20200320/DetectLymphRequest.py
aliyunsdkimageprocess/request/v20200320/DetectPancRequest.py
aliyunsdkimageprocess/request/v20200320/DetectRibFractureRequest.py
aliyunsdkimageprocess/request/v20200320/DetectSkinDiseaseRequest.py
aliyunsdkimageprocess/request/v20200320/DetectSpineMRIRequest.py
aliyunsdkimageprocess/request/v20200320/FeedbackSessionRequest.py
aliyunsdkimageprocess/request/v20200320/GetAsyncJobResultRequest.py
aliyunsdkimageprocess/request/v20200320/PredictCVDRequest.py
aliyunsdkimageprocess/request/v20200320/RunCTRegistrationRequest.py
aliyunsdkimageprocess/request/v20200320/RunMedQARequest.py
aliyunsdkimageprocess/request/v20200320/ScreenCRCRequest.py
aliyunsdkimageprocess/request/v20200320/ScreenChestCTRequest.py
aliyunsdkimageprocess/request/v20200320/ScreenECRequest.py
aliyunsdkimageprocess/request/v20200320/ScreenGCRequest.py
aliyunsdkimageprocess/request/v20200320/ScreenLCRequest.py
aliyunsdkimageprocess/request/v20200320/SegmentLymphNodeRequest.py
aliyunsdkimageprocess/request/v20200320/SegmentOARRequest.py
aliyunsdkimageprocess/request/v20200320/TargetVolumeSegmentRequest.py
aliyunsdkimageprocess/request/v20200320/TranslateMedRequest.py
aliyun_python_sdk_imageprocess-2.0.7.dist-info/LICENSE
aliyun_python_sdk_imageprocess-2.0.7.dist-info/METADATA
aliyun_python_sdk_imageprocess-2.0.7.dist-info/WHEEL
aliyun_python_sdk_imageprocess-2.0.7.dist-info/top_level.txt
aliyun_python_sdk_imageprocess-2.0.7.dist-info/RECORD
